cosmix/__init__.py
cosmix/__main__.py
cosmix/api/__init__.py
cosmix/api/config.py
cosmix/api/instance.py
cosmix/api/logger.py
cosmix/api/maven.py
cosmix/api/mod.py
cosmix/api/net.py
cosmix/api/paths.py
cosmix/api/versions.py
cosmix_launcher-1.1.1.dist-info/METADATA
cosmix_launcher-1.1.1.dist-info/WHEEL
cosmix_launcher-1.1.1.dist-info/entry_points.txt
cosmix_launcher-1.1.1.dist-info/RECORD
