Metadata-Version: 2.3
Name: cosmix-launcher
Version: 1.1.1
Summary: A dead simple CLI-based launcher for Cosmic Reach and Cosmic Quilt
Project-URL: Homepage, https://codeberg.org/EmmaTheMartian/cosmix
Project-URL: Issues, https://codeberg.org/EmmaTheMartian/cosmix/issues
Author-email: EmmaTheMartian <emmathemartian@gmail.com>
Classifier: License :: OSI Approved :: MIT License
Classifier: Programming Language :: Python :: 3
Requires-Python: >=3.10
Requires-Dist: click
Requires-Dist: click-aliases
Requires-Dist: crm1
Requires-Dist: hjson
Requires-Dist: java-manifest
Requires-Dist: requests
Requires-Dist: send2trash
Requires-Dist: tqdm
